{"cameraMode":{"drawMode":0,"name":"Shaded","section":"Shading Mode"},"sceneLighting":true,"audioPlay":false,"sceneViewState":{"showFog":true,"showMaterialUpdate":false,"showSkybox":true,"showFlares":true,"showImageEffects":true,"showParticleSystems":true},"in2DMode":false,"pivot":{"x":-46.51051712036133,"y":13.181564331054688,"z":2.7543575763702394},"rotation":{"x":0.057358380407094958,"y":0.6864840984344482,"z":0.05448174476623535,"w":-0.722844660282135},"size":62.09988021850586,"orthographic":false}